README.md
setup.py
autoreload/__init__.py
autoreload/__main__.py
autoreload/config.py
autoreload/path.py
autoreload/render.py
autoreload/run.py
autoreload.egg-info/PKG-INFO
autoreload.egg-info/SOURCES.txt
autoreload.egg-info/dependency_links.txt
autoreload.egg-info/requires.txt
autoreload.egg-info/top_level.txt