Metadata-Version: 1.1
Name: autoreload
Version: 0.1
Summary: Watch your code live reload in the browser
Home-page: https://github.com/ChillFish8/autoreload
Author: CF8
Author-email: hburt2003@gmail.com
License: MIT
Download-URL: https://github.com/ChillFish8/autoreload/archive/0.1.0.tar.gz
Keywords: live,auto,reloading,web development,web
Platform: UNKNOWN
Classifier: Development Status :: 3 - Alpha
Classifier: Intended Audience :: Developers
Classifier: Topic :: Software Development :: Build Tools
Classifier: License :: OSI Approved :: MIT License
Classifier: Programming Language :: Python :: 3
Classifier: Programming Language :: Python :: 3.6
Classifier: Programming Language :: Python :: 3.7
Classifier: Programming Language :: Python :: 3.8
